rio_color/__init__.py
rio_color/colorspace.c
rio_color/colorspace.cpython-39-darwin.so
rio_color/colorspace.pyx
rio_color/operations.py
rio_color/utils.py
rio_color/workers.py
rio_color/scripts/__init__.py
rio_color/scripts/cli.py
rio_color-2.0.1.dist-info/LICENSE
rio_color-2.0.1.dist-info/METADATA
rio_color-2.0.1.dist-info/WHEEL
rio_color-2.0.1.dist-info/entry_points.txt
rio_color-2.0.1.dist-info/top_level.txt
rio_color-2.0.1.dist-info/RECORD
