Metadata-Version: 2.1
Name: rio-color
Version: 2.0.1
Summary: Color correction plugin for rasterio
Home-page: https://github.com/mapbox/rio-color
Author: Charlie Loyd
Author-email: charlie@mapbox.com
License: BSD
Classifier: Development Status :: 5 - Production/Stable
Classifier: Intended Audience :: Developers
Classifier: Intended Audience :: Science/Research
Classifier: License :: OSI Approved :: MIT License
Classifier: Programming Language :: Cython
Classifier: Programming Language :: Python :: 3.9
Classifier: Programming Language :: Python :: 3.10
Classifier: Programming Language :: Python :: 3.11
Classifier: Programming Language :: Python :: 3.12
Classifier: Topic :: Multimedia :: Graphics :: Graphics Conversion
Classifier: Topic :: Scientific/Engineering :: GIS
Requires-Python: >=3.9
License-File: LICENSE
Requires-Dist: click>=8.0
Requires-Dist: rasterio~=1.4
Requires-Dist: rio-mucho
Provides-Extra: test
Requires-Dist: pytest; extra == "test"
Requires-Dist: colormath==3.0.0; extra == "test"
Requires-Dist: pytest-cov; extra == "test"
Requires-Dist: codecov; extra == "test"
